{"nodes": [{"id": "home_phill_defilade_readme_md", "label": "README.md", "file_type": "document", "source_file": "README.md", "source_location": "L1"}, {"id": "home_phill_defilade_readme_defilade", "label": "Defilade", "file_type": "document", "source_file": "README.md", "source_location": "L1"}, {"id": "home_phill_defilade_readme_60_second_quickstart", "label": "60-second quickstart", "file_type": "document", "source_file": "README.md", "source_location": "L17"}, {"id": "home_phill_defilade_readme_hard_constraints", "label": "Hard constraints", "file_type": "document", "source_file": "README.md", "source_location": "L47"}, {"id": "home_phill_defilade_readme_limitations_read_before_trusting_the_output", "label": "Limitations (read before trusting the output)", "file_type": "document", "source_file": "README.md", "source_location": "L54"}, {"id": "home_phill_defilade_readme_artifact_handling", "label": "Artifact handling", "file_type": "document", "source_file": "README.md", "source_location": "L64"}, {"id": "home_phill_defilade_readme_repository_layout", "label": "Repository layout", "file_type": "document", "source_file": "README.md", "source_location": "L71"}], "edges": [{"source": "home_phill_defilade_readme_md", "target": "home_phill_defilade_readme_defilade", "relation": "contains", "confidence": "EXTRACTED", "source_file": "README.md", "source_location": "L1", "weight": 1.0}, {"source": "home_phill_defilade_readme_defilade", "target": "home_phill_defilade_readme_60_second_quickstart", "relation": "contains", "confidence": "EXTRACTED", "source_file": "README.md", "source_location": "L17", "weight": 1.0}, {"source": "home_phill_defilade_readme_defilade", "target": "home_phill_defilade_readme_hard_constraints", "relation": "contains", "confidence": "EXTRACTED", "source_file": "README.md", "source_location": "L47", "weight": 1.0}, {"source": "home_phill_defilade_readme_defilade", "target": "home_phill_defilade_readme_limitations_read_before_trusting_the_output", "relation": "contains", "confidence": "EXTRACTED", "source_file": "README.md", "source_location": "L54", "weight": 1.0}, {"source": "home_phill_defilade_readme_defilade", "target": "home_phill_defilade_readme_artifact_handling", "relation": "contains", "confidence": "EXTRACTED", "source_file": "README.md", "source_location": "L64", "weight": 1.0}, {"source": "home_phill_defilade_readme_defilade", "target": "home_phill_defilade_readme_repository_layout", "relation": "contains", "confidence": "EXTRACTED", "source_file": "README.md", "source_location": "L71", "weight": 1.0}], "input_tokens": 0, "output_tokens": 0}